smart_label_plotter/__init__.py
smart_label_plotter/smart_label_plotter.py
smart_label_plotter-0.0.2.dist-info/METADATA
smart_label_plotter-0.0.2.dist-info/WHEEL
smart_label_plotter-0.0.2.dist-info/top_level.txt
smart_label_plotter-0.0.2.dist-info/RECORD
