Metadata-Version: 2.4
Name: smart-label-plotter
Version: 0.0.2
Summary: A patch for Ultralytics YOLO to optimize label layout using labellayout.
Author: Leon
Classifier: Programming Language :: Python :: 3
Classifier: License :: OSI Approved :: MIT License
Classifier: Operating System :: OS Independent
Requires-Python: >=3.8
Requires-Dist: numpy
Requires-Dist: opencv-python
Requires-Dist: Pillow
Requires-Dist: ultralytics
Requires-Dist: labellayout
Dynamic: author
Dynamic: classifier
Dynamic: description
Dynamic: description-content-type
Dynamic: requires-dist
Dynamic: requires-python
Dynamic: summary
